odoo/addons/account_fiscal_year/README.rst
odoo/addons/account_fiscal_year/__init__.py
odoo/addons/account_fiscal_year/__manifest__.py
odoo/addons/account_fiscal_year/data/date_range_type.xml
odoo/addons/account_fiscal_year/i18n/account_fiscal_year.pot
odoo/addons/account_fiscal_year/i18n/ar.po
odoo/addons/account_fiscal_year/i18n/da.po
odoo/addons/account_fiscal_year/i18n/de.po
odoo/addons/account_fiscal_year/i18n/el_GR.po
odoo/addons/account_fiscal_year/i18n/es.po
odoo/addons/account_fiscal_year/i18n/es_CO.po
odoo/addons/account_fiscal_year/i18n/es_EC.po
odoo/addons/account_fiscal_year/i18n/fi.po
odoo/addons/account_fiscal_year/i18n/fr.po
odoo/addons/account_fiscal_year/i18n/fr_FR.po
odoo/addons/account_fiscal_year/i18n/hr.po
odoo/addons/account_fiscal_year/i18n/hr_HR.po
odoo/addons/account_fiscal_year/i18n/it.po
odoo/addons/account_fiscal_year/i18n/pt.po
odoo/addons/account_fiscal_year/i18n/pt_BR.po
odoo/addons/account_fiscal_year/i18n/sk.po
odoo/addons/account_fiscal_year/i18n/sl.po
odoo/addons/account_fiscal_year/i18n/tr.po
odoo/addons/account_fiscal_year/i18n/tr_TR.po
odoo/addons/account_fiscal_year/models/__init__.py
odoo/addons/account_fiscal_year/models/date_range_type.py
odoo/addons/account_fiscal_year/models/res_company.py
odoo/addons/account_fiscal_year/static/description/icon.png
odoo/addons/account_fiscal_year/tests/__init__.py
odoo/addons/account_fiscal_year/tests/test_account_fiscal_year.py
odoo/addons/account_fiscal_year/views/date_range_type.xml
odoo11_addon_account_fiscal_year-11.0.1.0.0.99.dev22.dist-info/METADATA
odoo11_addon_account_fiscal_year-11.0.1.0.0.99.dev22.dist-info/WHEEL
odoo11_addon_account_fiscal_year-11.0.1.0.0.99.dev22.dist-info/top_level.txt
odoo11_addon_account_fiscal_year-11.0.1.0.0.99.dev22.dist-info/RECORD
